odoo/addons/product_multi_ean/README.rst
odoo/addons/product_multi_ean/__init__.py
odoo/addons/product_multi_ean/__manifest__.py
odoo/addons/product_multi_ean/hooks.py
odoo/addons/product_multi_ean/i18n/am.po
odoo/addons/product_multi_ean/i18n/ar.po
odoo/addons/product_multi_ean/i18n/bg.po
odoo/addons/product_multi_ean/i18n/bs.po
odoo/addons/product_multi_ean/i18n/ca.po
odoo/addons/product_multi_ean/i18n/ca_ES.po
odoo/addons/product_multi_ean/i18n/cs.po
odoo/addons/product_multi_ean/i18n/da.po
odoo/addons/product_multi_ean/i18n/da_DK.po
odoo/addons/product_multi_ean/i18n/de.po
odoo/addons/product_multi_ean/i18n/el_GR.po
odoo/addons/product_multi_ean/i18n/en_GB.po
odoo/addons/product_multi_ean/i18n/es.po
odoo/addons/product_multi_ean/i18n/es_AR.po
odoo/addons/product_multi_ean/i18n/es_CO.po
odoo/addons/product_multi_ean/i18n/es_CR.po
odoo/addons/product_multi_ean/i18n/es_EC.po
odoo/addons/product_multi_ean/i18n/es_ES.po
odoo/addons/product_multi_ean/i18n/es_MX.po
odoo/addons/product_multi_ean/i18n/es_PE.po
odoo/addons/product_multi_ean/i18n/es_PY.po
odoo/addons/product_multi_ean/i18n/es_VE.po
odoo/addons/product_multi_ean/i18n/eu.po
odoo/addons/product_multi_ean/i18n/fa.po
odoo/addons/product_multi_ean/i18n/fi.po
odoo/addons/product_multi_ean/i18n/fr.po
odoo/addons/product_multi_ean/i18n/fr_CA.po
odoo/addons/product_multi_ean/i18n/fr_CH.po
odoo/addons/product_multi_ean/i18n/fr_FR.po
odoo/addons/product_multi_ean/i18n/gl.po
odoo/addons/product_multi_ean/i18n/gl_ES.po
odoo/addons/product_multi_ean/i18n/he.po
odoo/addons/product_multi_ean/i18n/hr.po
odoo/addons/product_multi_ean/i18n/hr_HR.po
odoo/addons/product_multi_ean/i18n/it.po
odoo/addons/product_multi_ean/i18n/ja.po
odoo/addons/product_multi_ean/i18n/ko.po
odoo/addons/product_multi_ean/i18n/lt.po
odoo/addons/product_multi_ean/i18n/lt_LT.po
odoo/addons/product_multi_ean/i18n/lv.po
odoo/addons/product_multi_ean/i18n/mk.po
odoo/addons/product_multi_ean/i18n/mn.po
odoo/addons/product_multi_ean/i18n/nb.po
odoo11_addon_product_multi_ean-11.0.2.0.0.dist-info/METADATA
odoo11_addon_product_multi_ean-11.0.2.0.0.dist-info/WHEEL
odoo11_addon_product_multi_ean-11.0.2.0.0.dist-info/top_level.txt
odoo11_addon_product_multi_ean-11.0.2.0.0.dist-info/RECORD
