Metadata-Version: 2.1
Name: odoo11-addon-product-multi-ean
Version: 11.0.2.0.0
Summary: Multiple EAN13 on products
Home-page: https://github.com/OCA/stock-logistics-barcode
Author: Camptocamp, Trey, Tecnativa, QubiQ, Odoo Community Association (OCA)
Author-email: support@odoo-community.org
License: AGPL-3
Platform: UNKNOWN
Classifier: Programming Language :: Python
Classifier: Framework :: Odoo
Classifier: License :: OSI Approved :: GNU Affero General Public License v3
Requires-Python: >=2.7, !=3.0.*, !=3.1.*, !=3.2.*, !=3.3.*, !=3.4.*
Requires-Dist: odoo (<11.1dev,>=11.0a)
